random_address/__init__.py
random_address/addresses-us-all.min.json
random_address/random_address.py
random_address-1.3.0.dist-info/licenses/LICENSE.txt
random_address-1.3.0.dist-info/METADATA
random_address-1.3.0.dist-info/WHEEL
random_address-1.3.0.dist-info/top_level.txt
random_address-1.3.0.dist-info/RECORD
